imgtotxt/__init__.py
imgtotxt/__main__.py
imgtotxt/app.py
imgtotxt/ocr.py
imgtotxt/state.py
imgtotxt-0.1.2.dist-info/LICENSE
imgtotxt-0.1.2.dist-info/METADATA
imgtotxt-0.1.2.dist-info/WHEEL
imgtotxt-0.1.2.dist-info/entry_points.txt
imgtotxt-0.1.2.dist-info/top_level.txt
imgtotxt-0.1.2.dist-info/RECORD
